secbulkdownload/__init__.py
secbulkdownload/config.py
secbulkdownload/limiter.py
secbulkdownload/secfiling.py
secbulkdownload/secmeta.py
secbulkdownload/setup.py
secbulkdownload/utils.py
secbulkdownload-0.0.2.dist-info/METADATA
secbulkdownload-0.0.2.dist-info/WHEEL
secbulkdownload-0.0.2.dist-info/top_level.txt
secbulkdownload-0.0.2.dist-info/RECORD
